wbget/__init__.py
wbget/_version.py
wbget/qhtml.html
wbget/wbget.py
wbget-0.0.2.dist-info/entry_points.txt
wbget-0.0.2.dist-info/licenses/LICENSE
wbget-0.0.2.dist-info/WHEEL
wbget-0.0.2.dist-info/METADATA
wbget-0.0.2.dist-info/RECORD
