Metadata-Version: 2.4
Name: wbget
Version: 0.0.2
Summary: Wikibase GET
Author: Darron Broad
Requires-Python: >=3.9
Classifier: Programming Language :: Python :: 3
Classifier: Operating System :: OS Independent
License-File: LICENSE
Requires-Dist: WikibaseIntegrator>=0.12
Requires-Dist: jinja2
Project-URL: Documentation, https://wiki.kewl.org/projects:wbget
Project-URL: Source, https://hg.kewl.org/pub/wbget
